{
  "annotations": {
    "list": []
  },
  "description": "SAHOOL Service Readiness and Health",
  "editable": true,
  "fiscalYearStartMonth": 0,
  "graphTooltip": 1,
  "id": null,
  "links": [],
  "liveNow": false,
  "panels": [
    {
      "datasource": {
        "type": "prometheus",
        "uid": "prometheus"
      },
      "fieldConfig": {
        "defaults": {
          "color": {
            "mode": "thresholds"
          },
          "mappings": [
            { "options": { "0": { "color": "red", "text": "Down" }, "1": { "color": "green", "text": "Up" } }, "type": "value" }
          ],
          "thresholds": {
            "mode": "absolute",
            "steps": [
              { "color": "red", "value": null },
              { "color": "green", "value": 1 }
            ]
          }
        }
      },
      "gridPos": { "h": 8, "w": 24, "x": 0, "y": 0 },
      "id": 1,
      "options": {
        "colorMode": "background",
        "graphMode": "none",
        "justifyMode": "auto",
        "orientation": "horizontal",
        "reduceOptions": {
          "calcs": ["lastNotNull"],
          "fields": "",
          "values": false
        },
        "textMode": "value_and_name"
      },
      "targets": [
        {
          "expr": "up{namespace=\"sahool\"}",
          "legendFormat": "{{job}}",
          "refId": "A"
        }
      ],
      "title": "Service Status",
      "type": "stat"
    },
    {
      "datasource": {
        "type": "prometheus",
        "uid": "prometheus"
      },
      "fieldConfig": {
        "defaults": {
          "color": {
            "mode": "palette-classic"
          },
          "unit": "reqps"
        }
      },
      "gridPos": { "h": 8, "w": 12, "x": 0, "y": 8 },
      "id": 2,
      "options": {
        "legend": {
          "calcs": ["mean", "max"],
          "displayMode": "table",
          "placement": "right"
        },
        "tooltip": {
          "mode": "multi",
          "sort": "desc"
        }
      },
      "targets": [
        {
          "expr": "sum by (service) (rate(http_requests_total{namespace=\"sahool\"}[5m]))",
          "legendFormat": "{{service}}",
          "refId": "A"
        }
      ],
      "title": "Request Rate by Service",
      "type": "timeseries"
    },
    {
      "datasource": {
        "type": "prometheus",
        "uid": "prometheus"
      },
      "fieldConfig": {
        "defaults": {
          "color": {
            "mode": "palette-classic"
          },
          "unit": "s"
        }
      },
      "gridPos": { "h": 8, "w": 12, "x": 12, "y": 8 },
      "id": 3,
      "options": {
        "legend": {
          "calcs": ["mean", "max"],
          "displayMode": "table",
          "placement": "right"
        },
        "tooltip": {
          "mode": "multi",
          "sort": "desc"
        }
      },
      "targets": [
        {
          "expr": "histogram_quantile(0.95, sum by (service, le) (rate(http_request_duration_seconds_bucket{namespace=\"sahool\"}[5m])))",
          "legendFormat": "{{service}} P95",
          "refId": "A"
        }
      ],
      "title": "Response Time P95 by Service",
      "type": "timeseries"
    },
    {
      "datasource": {
        "type": "prometheus",
        "uid": "prometheus"
      },
      "fieldConfig": {
        "defaults": {
          "color": {
            "mode": "palette-classic"
          },
          "unit": "percent"
        }
      },
      "gridPos": { "h": 8, "w": 24, "x": 0, "y": 16 },
      "id": 4,
      "options": {
        "legend": {
          "calcs": ["mean", "max"],
          "displayMode": "table",
          "placement": "right"
        },
        "tooltip": {
          "mode": "multi",
          "sort": "desc"
        }
      },
      "targets": [
        {
          "expr": "(sum by (service) (rate(http_requests_total{namespace=\"sahool\", status=~\"5..\"}[5m])) / sum by (service) (rate(http_requests_total{namespace=\"sahool\"}[5m]))) * 100",
          "legendFormat": "{{service}}",
          "refId": "A"
        }
      ],
      "title": "Error Rate by Service (%)",
      "type": "timeseries"
    },
    {
      "datasource": {
        "type": "prometheus",
        "uid": "prometheus"
      },
      "fieldConfig": {
        "defaults": {
          "color": {
            "mode": "palette-classic"
          }
        }
      },
      "gridPos": { "h": 8, "w": 24, "x": 0, "y": 24 },
      "id": 5,
      "options": {
        "legend": {
          "calcs": [],
          "displayMode": "table",
          "placement": "right"
        },
        "tooltip": {
          "mode": "multi",
          "sort": "desc"
        }
      },
      "targets": [
        {
          "expr": "increase(kube_pod_container_status_restarts_total{namespace=\"sahool\"}[1h])",
          "legendFormat": "{{pod}}",
          "refId": "A"
        }
      ],
      "title": "Pod Restarts (Last Hour)",
      "type": "timeseries"
    }
  ],
  "refresh": "30s",
  "schemaVersion": 38,
  "style": "dark",
  "tags": ["sahool", "service", "readiness"],
  "templating": {
    "list": [
      {
        "current": {},
        "datasource": {
          "type": "prometheus",
          "uid": "prometheus"
        },
        "definition": "label_values(up{namespace=\"sahool\"}, job)",
        "hide": 0,
        "includeAll": true,
        "multi": true,
        "name": "service",
        "query": {
          "query": "label_values(up{namespace=\"sahool\"}, job)",
          "refId": "StandardVariableQuery"
        },
        "refresh": 1,
        "type": "query"
      }
    ]
  },
  "time": {
    "from": "now-3h",
    "to": "now"
  },
  "timepicker": {},
  "timezone": "",
  "title": "SAHOOL Service Readiness",
  "uid": "sahool-service-readiness",
  "version": 1
}
